gcd/master.sv
module master(
  input logic [3:0] op_a_i,
  input logic [3:0] op_b_i,
  input logic       busy_i,
  input logic       valid_i,
  input logic [3:0] result_val_i,

  output logic [3:0] result_val_o,
  output logic [3:0] a_o,
  output logic [3:0] b_o,
  output logic       req_o,

  input logic clk_i
);

always_ff @(posedge clk_i) begin
    if ((op_a_i != 0) & (op_b_i != 0)) begin
      req_o <= 1'b1;
      if (!busy_i) begin
        a_o <= op_a_i;
        b_o <= op_b_i;
        req_o <= 1'b0;
      end
    end
end

assign result_val_o = valid_i ? result_val_i : 0;

endmodule

src/dff.sv
// This file is public domain, it can be freely copied without restrictions.
// SPDX-License-Identifier: CC0-1.0


module dff (
  input logic clk_i,
  input logic en,
  input logic [3:0] d,
  output logic[3:0] q
);

always_ff @(posedge clk_i) begin
  if (en)  q <= d;
  else     q <= q;
end

endmodule: dff

gcd/mux21.sv
module mux21(
  input  logic [3:0] in0,
  input  logic [3:0] in1,
  input  logic       sel,
  output logic [3:0] out
);

assign out = sel? in1: in0;

endmodule: mux21

gcd/mux41.sv
module mux41(
  input  logic [3:0] in0,
  input  logic [3:0] in1,
  input  logic [3:0] in2,
  input  logic [3:0] in3,
  input  logic [1:0] sel,
  output logic [3:0] out
);

always_comb begin
  case (sel)
    2'b11: out = in3;
    2'b10: out = in2;
    2'b01: out = in1;
    2'b00: out = in0;
  endcase
end

endmodule: mux41

gcd/slave.sv
module slave (
  input  logic       clk_i,rst_ni,
  input  logic [3:0] op_a_i, op_b_i,
  input  logic       req_i,

  output logic [3:0] result_val_o,
  output logic       busy_o, valid_o
);
  //declare variable
  logic [3:0] A;
  logic [3:0] B;
  logic [3:0] sub_ab;
  logic [3:0] outa;
  logic [3:0] outb;
  logic [1:0] a_sel;
  logic       b_sel;

  typedef enum logic [1:0] {
    WAIT = 2'd0,
    CALC = 2'd1,
    DONE = 2'd2
  } fsm_state;

  fsm_state state, next_state;

  always_comb begin
      case (state)
        WAIT: begin
          valid_o = 1'b0;
          busy_o  = 1'b0;
          if (req_i) begin
            next_state = CALC;
            a_sel = 2'd0;
            b_sel = 1'b0;
          end
          else  next_state = WAIT;
        end

        CALC: begin
          valid_o = 1'b0;
          busy_o  = 1'b1;
          if (b_zero) begin
            next_state = DONE;
          end
          else if (a_lt) begin
            a_sel = 2'd1;
            b_sel = 1'b1;
            next_state = CALC;
          end
          else begin
            a_sel = 2'd2;
            b_sel = 1'b1;
            next_state = CALC;
          end
        end
        DONE: begin
          valid_o = 1'b1;
          busy_o  = 1'b0;
          next_state = WAIT;
        end
      endcase
  end

  always_ff @(posedge clk_i) begin
    if (!rst_ni)  state <= WAIT;
    else      state <= next_state;
  end

  mux41 muxa(
    .in0(op_a_i),
    .in1(B),
    .in2(sub_ab),
    .in3(4'd0),
    .sel(a_sel),
    .out(outa)
  );

  mux21 muxb(
    .in0(op_b_i),
    .in1(A),
    .sel(b_sel),
    .out(outb)
  );

  dff a_ff(
    .clk_i(clk_i),
    .en(1'b1),
    .d(outa),
    .q(A)
  );

  dff b_ff(
    .clk_i(clk_i),
    .en(1'b1),
    .d(outb),
    .q(B)
  );
  assign b_zero = (B == 0);
  assign a_lt   = ((A < B) ? 1 : 0);
  assign sub_ab = A - B;
  assign result_val_o  = A;

endmodule

src/top.sv
module top(
  input  logic       clk_i,
  input  logic       rst_ni,
  input  logic [3:0] a_i,
  input  logic [3:0] b_i,
  output logic [3:0] result_val_o
);

  logic [3:0] a_data_mas_to_sla, b_data_mas_to_sla, result_val;
  logic req, busy, valid;

  slave slv(
    .clk_i          (clk_i),
    .rst_ni         (rst_ni),
    .op_a_i         (a_data_mas_to_sla),
    .op_b_i         (b_data_mas_to_sla),
    .req_i          (req),
    .busy_o         (busy),
    .valid_o        (valid),
    .result_val_o   (result_val)
  );

  master mter(
    .op_a_i         (a_i),
    .op_b_i         (b_i),
    .busy_i         (busy),
    .valid_i        (valid),
    .result_val_i   (result_val),
    .result_val_o   (result_val_o),
    .a_o            (a_data_mas_to_sla),
    .b_o            (b_data_mas_to_sla),
    .clk_i          (clk_i),
    .req_o          (req)
  );
  initial begin
    $dumpfile("dump.vcd");
    $dumpvars(1, top);
  end
endmodule

cocotb/run/dump.vcd
$date
	Tue Aug 22 22:06:21 2023
$end
$version
	Icarus Verilog
$end
$timescale
	1ps
$end
$scope module top $end
$var wire 4 ! a_i [3:0] $end
$var wire 4 " b_i [3:0] $end
$var wire 1 # clk_i $end
$var wire 1 $ rst_ni $end
$var wire 1 % valid $end
$var wire 4 & result_val_o [3:0] $end
$var wire 4 ' result_val [3:0] $end
$var wire 1 ( req $end
$var wire 1 ) busy $end
$var wire 4 * b_data_mas_to_sla [3:0] $end
$var wire 4 + a_data_mas_to_sla [3:0] $end
$upscope $end
$enddefinitions $end
$comment Show the parameter values. $end
$dumpall
$end
#0
$dumpvars
bx00 +
b0x0x *
x)
x(
bx '
bx &
x%
z$
0#
b101 "
b1100 !
$end
#5000
b101 *
b1100 +
b0 &
0)
0%
0$
1(
1#
#6000
1$
#10000
0#
#15000
b0 *
b0 +
1)
b1100 '
1#
#20000
0#
#25000
b111 '
1#
#30000
0#
#35000
b10 '
1#
#40000
0#
#45000
b101 '
1#
#50000
0#
#55000
b11 '
1#
#60000
0#
#65000
b1 '
1#
#70000
0#
#75000
b10 '
1#
#80000
0#
#85000
b1 '
1#
#90000
0#
#95000
b0 '
1#
#100000
0#
#105000
b1 '
1#
#110000
0#
#115000
b1 &
1%
1#
#120000
0#
#125000
b101 *
b1100 +
b0 &
0)
0%
1#
