src/FIFO2.sv
module FIFO2
#(
  parameter DEPTH  =  8,
  parameter DATA_WIDTH  =  4
)(
  input  logic  clk_i, rst_ni,
  input  logic  wr_en, rd_en,
  input  logic  [DATA_WIDTH-1:0] data_i,
  output logic  empty_o,
  output logic  [DATA_WIDTH-1:0] data_o
);

  logic [$clog2(DEPTH) : 0] w_ptr, r_ptr;
  logic [DATA_WIDTH-1:0] fifo [DEPTH];
  logic full;

  //Set default value when reset
  always_ff @(posedge clk_i or negedge rst_ni) begin
    if (!rst_ni) begin
      w_ptr  <= 0;
      r_ptr  <= 0;
      data_o <= 0;
    end
    else begin
      if  (wr_en & !full)  begin
        fifo[w_ptr[2:0]] <= data_i;
        w_ptr <= w_ptr + 1;
      end
      if  (rd_en & !empty_o)  begin
        data_o <= fifo[r_ptr[2:0]];
        r_ptr  <= r_ptr + 1;
        fifo[r_ptr[2:0]] <= 0;
      end
    end
  end
  assign full  = ({~w_ptr[3], w_ptr[2:0]} == r_ptr);
  assign empty_o = (w_ptr == r_ptr);
endmodule

gcd/master.sv
module master(
  input logic [3:0] op_a_i,
  input logic [3:0] op_b_i,
  input logic       busy_i,
  input logic       valid_i,
  input logic [3:0] result_val_i,

  output logic [3:0] result_val_o,
  output logic [3:0] a_o,
  output logic [3:0] b_o,
  output logic       req_o,

  input logic clk_i
);

always_ff @(posedge clk_i) begin
    if ((op_a_i != 0) & (op_b_i != 0)) begin
      req_o <= 1'b1;
      if (!busy_i) begin
        a_o <= op_a_i;
        b_o <= op_b_i;
        req_o <= 1'b0;
      end
    end
end

assign result_val_o = valid_i ? result_val_i : 0;

endmodule

src/dff.sv
// This file is public domain, it can be freely copied without restrictions.
// SPDX-License-Identifier: CC0-1.0


module dff (
  input logic clk_i,
  input logic en,
  input logic [3:0] d,
  output logic[3:0] q
);

always_ff @(posedge clk_i) begin
  if (en)  q <= d;
  else     q <= q;
end

endmodule: dff

gcd/mux21.sv
module mux21(
  input  logic [3:0] in0,
  input  logic [3:0] in1,
  input  logic       sel,
  output logic [3:0] out
);

assign out = sel? in1: in0;

endmodule: mux21

gcd/mux41.sv
module mux41(
  input  logic [3:0] in0,
  input  logic [3:0] in1,
  input  logic [3:0] in2,
  input  logic [3:0] in3,
  input  logic [1:0] sel,
  output logic [3:0] out
);

always_comb begin
  case (sel)
    2'b11: out = in3;
    2'b10: out = in2;
    2'b01: out = in1;
    2'b00: out = in0;
  endcase
end

endmodule: mux41

gcd/slave.sv
module slave (
  input  logic       clk_i,rst_ni,
  input  logic [3:0] op_a_i, op_b_i,
  input  logic       req_i,

  output logic [3:0] result_val_o,
  output logic       busy_o, valid_o
);
  //declare variable
  logic [3:0] A;
  logic [3:0] B;
  logic [3:0] sub_ab;
  logic [3:0] outa;
  logic [3:0] outb;
  logic [1:0] a_sel;
  logic       b_sel;

  typedef enum logic [1:0] {
    WAIT = 2'd0,
    CALC = 2'd1,
    DONE = 2'd2
  } fsm_state;

  fsm_state state, next_state;

  always_comb begin
      case (state)
        WAIT: begin
          valid_o = 1'b0;
          busy_o  = 1'b0;
          if (req_i) begin
            next_state = CALC;
            a_sel = 2'd0;
            b_sel = 1'b0;
          end
          else  next_state = WAIT;
        end

        CALC: begin
          valid_o = 1'b0;
          busy_o  = 1'b1;
          if (b_zero) begin
            next_state = DONE;
          end
          else if (a_lt) begin
            a_sel = 2'd1;
            b_sel = 1'b1;
            next_state = CALC;
          end
          else begin
            a_sel = 2'd2;
            b_sel = 1'b1;
            next_state = CALC;
          end
        end
        DONE: begin
          valid_o = 1'b1;
          busy_o  = 1'b0;
          next_state = WAIT;
        end
      endcase
  end

  always_ff @(posedge clk_i) begin
    if (!rst_ni)  state <= WAIT;
    else      state <= next_state;
  end

  mux41 muxa(
    .in0(op_a_i),
    .in1(B),
    .in2(sub_ab),
    .in3(4'd0),
    .sel(a_sel),
    .out(outa)
  );

  mux21 muxb(
    .in0(op_b_i),
    .in1(A),
    .sel(b_sel),
    .out(outb)
  );

  dff a_ff(
    .clk_i(clk_i),
    .en(1'b1),
    .d(outa),
    .q(A)
  );

  dff b_ff(
    .clk_i(clk_i),
    .en(1'b1),
    .d(outb),
    .q(B)
  );
  assign b_zero = (B == 0);
  assign a_lt   = ((A < B) ? 1 : 0);
  assign sub_ab = A - B;
  assign result_val_o  = A;

endmodule

src/gcd.sv
module gcd(
  input  logic       clk_i,
  input  logic       rst_ni,
  input  logic [3:0] a_i,
  input  logic [3:0] b_i,
  output logic       busy_o,
  output logic       valid_o,
  output logic [3:0] result_val_o
);

  logic [3:0] a_data_mas_to_sla, b_data_mas_to_sla, result_val;
  logic req, busy, valid;

  slave slv(
    .clk_i          (clk_i),
    .rst_ni         (rst_ni),
    .op_a_i         (a_data_mas_to_sla),
    .op_b_i         (b_data_mas_to_sla),
    .req_i          (req),
    .busy_o         (busy),
    .valid_o        (valid),
    .result_val_o   (result_val)
  );

  master mter(
    .op_a_i         (a_i),
    .op_b_i         (b_i),
    .busy_i         (busy),
    .valid_i        (valid),
    .result_val_i   (result_val),
    .result_val_o   (result_val_o),
    .a_o            (a_data_mas_to_sla),
    .b_o            (b_data_mas_to_sla),
    .clk_i          (clk_i),
    .req_o          (req)
  );

  assign busy_o = busy;
  assign valid_o = valid;
endmodule

src/FIFO1.sv
module FIFO1
#(
  parameter DEPTH  =  8,
  parameter DATA_WIDTH  =  4
)(
  input  logic  clk_i, rst_ni,
  input  logic  wr_en, rd_en,
  input  logic  [DATA_WIDTH-1:0] data_i,
  output logic  full_o,
  output logic  [DATA_WIDTH-1:0] data_o
);

  logic [$clog2(DEPTH) : 0] w_ptr, r_ptr;
  logic [DATA_WIDTH-1:0] fifo [DEPTH];
  logic empty;

  //Set default value when reset
  always_ff @(posedge clk_i or negedge rst_ni) begin
    if (!rst_ni) begin
      w_ptr  <= 0;
      r_ptr  <= 0;
      data_o <= 0;
    end
    else begin
      if  (wr_en & !full_o)  begin
        fifo[w_ptr[2:0]] <= data_i;
        w_ptr <= w_ptr + 1;
      end
      if  (rd_en & !empty)  begin
        data_o <= fifo[r_ptr[2:0]];
        r_ptr  <= r_ptr + 1;
        fifo[r_ptr[2:0]] <= 0;
      end
    end
  end
  assign full_o  = ({~w_ptr[3], w_ptr[2:0]} == r_ptr);
  assign empty = (w_ptr == r_ptr);
endmodule

src/ifc_gcd.sv
module ifc_gcd (
  input  logic  [3:0] a_data,
  input  logic        a_en  ,
  input  logic  [3:0] b_data,
  input  logic        b_en  ,
  input  logic        y_en  ,
  input  logic        clk_i ,
  input  logic        rst_ni,

  output logic        b_rdy ,
  output logic  [3:0] y_data,
  output logic        a_rdy ,
  output logic        y_rdy
);
logic [3:0] a,b,result;
logic a_full, b_full, busy, valid, y_empty;

FIFO1 data_a (
  .clk_i    (clk_i),
  .rst_ni   (rst_ni),
  .wr_en    (a_en),
  .rd_en    (!busy),
  .data_i   (a_data),
  .full_o   (a_full),
  .data_o   (a)
);

FIFO1 data_b (
  .clk_i    (clk_i),
  .rst_ni   (rst_ni),
  .wr_en    (b_en),
  .rd_en    (!busy),
  .data_i   (b_data),
  .full_o   (b_full),
  .data_o   (b)
);

gcd GCD (
  .clk_i        (clk_i),
  .rst_ni       (rst_ni),
  .a_i          (a),
  .b_i          (b),
  .busy_o       (busy),
  .valid_o      (valid),
  .result_val_o (result)
);

FIFO2 data_y (
  .clk_i    (clk_i),
  .rst_ni   (rst_ni),
  .wr_en    (valid),
  .rd_en    (y_en),
  .data_i   (result),
  .empty_o  (y_empty),
  .data_o   (y_data)
);

assign a_rdy = (!a_full);
assign b_rdy = (!b_full);
assign y_rdy = (!y_empty);

  initial begin
    $dumpfile("dump.vcd");
    $dumpvars(1, ifc_gcd);
  end

endmodule

cocotb/run/dump.vcd
$date
	Wed Aug 23 19:55:06 2023
$end
$version
	Icarus Verilog
$end
$timescale
	1ps
$end
$scope module ifc_gcd $end
$var wire 4 ! a_data [3:0] $end
$var wire 1 " a_en $end
$var wire 4 # b_data [3:0] $end
$var wire 1 $ b_en $end
$var wire 1 % clk_i $end
$var wire 1 & rst_ni $end
$var wire 1 ' y_en $end
$var wire 1 ( y_rdy $end
$var wire 1 ) y_empty $end
$var wire 4 * y_data [3:0] $end
$var wire 1 + valid $end
$var wire 4 , result [3:0] $end
$var wire 1 - busy $end
$var wire 1 . b_rdy $end
$var wire 1 / b_full $end
$var wire 4 0 b [3:0] $end
$var wire 1 1 a_rdy $end
$var wire 1 2 a_full $end
$var wire 4 3 a [3:0] $end
$upscope $end
$enddefinitions $end
$comment Show the parameter values. $end
$dumpall
$end
#0
$dumpvars
bx 3
x2
x1
bx 0
x/
x.
x-
bx ,
x+
bx *
x)
x(
z'
z&
0%
z$
b101 #
z"
b1100 !
$end
#5000
b0 ,
1.
0/
11
02
0-
0+
b0 *
0(
1)
b0 0
b0 3
0&
1%
#6000
1&
#10000
0%
#15000
1"
1$
1%
#20000
0%
#25000
0'
1%
#30000
0%
#35000
b1100 3
b101 0
1%
#40000
0%
#45000
1%
#50000
0%
#55000
1-
1%
#60000
0%
#65000
1%
#70000
0%
#75000
1%
#80000
0%
#85000
1%
#90000
0%
#95000
1%
#100000
0%
#105000
1%
#110000
0%
#115000
1%
#120000
0%
#125000
0.
1/
01
12
1%
#130000
0%
#135000
1%
#140000
0%
#145000
1%
#150000
0%
#155000
b1 ,
1+
1%
#160000
0%
#165000
b0 ,
0-
0+
1(
0)
1%
#170000
0%
#175000
1'
1-
11
02
1.
0/
1%
#180000
0%
#185000
0.
1/
01
12
0(
1)
b1 *
1%
