src/master.sv
module master(
  input  logic [3:0] op_a_i,
  input  logic [3:0] op_b_i,
  input  logic       a_en,
  input  logic       b_en,
  input  logic       busy_i,
  input  logic       valid_i,
  input  logic [3:0] result_val_i,

  output logic [3:0] result_val_o,
  output logic [3:0] a_o,
  output logic [3:0] b_o,
  output logic       req_o,

  input  logic       clk_i
);
always_ff @(posedge clk_i) begin
  if (a_en)  a_o <= op_a_i;
  else if (req_o) a_o <= 0;
  else a_o <= a_o;

  if (b_en)  b_o <= op_b_i;
  else if (req_o) b_o <= 0;
  else b_o <= b_o;
end

always_ff @(posedge clk_i) begin
    if ((a_o != 0) && (b_o != 0))
      req_o <= 1'b1;
    else if (!busy_i)
      req_o <= 1'b0;
end

assign result_val_o = valid_i ? result_val_i : 0;

endmodule

src/dff.sv
// This file is public domain, it can be freely copied without restrictions.
// SPDX-License-Identifier: CC0-1.0


module dff (
  input logic clk_i,
  input logic en,
  input logic [3:0] d,
  output logic[3:0] q
);

always_ff @(posedge clk_i) begin
  if (en)  q <= d;
  else     q <= q;
end

endmodule: dff

gcd/mux21.sv
module mux21(
  input  logic [3:0] in0,
  input  logic [3:0] in1,
  input  logic       sel,
  output logic [3:0] out
);

assign out = sel? in1: in0;

endmodule: mux21

gcd/mux41.sv
module mux41(
  input  logic [3:0] in0,
  input  logic [3:0] in1,
  input  logic [3:0] in2,
  input  logic [3:0] in3,
  input  logic [1:0] sel,
  output logic [3:0] out
);

always_comb begin
  case (sel)
    2'b11: out = in3;
    2'b10: out = in2;
    2'b01: out = in1;
    2'b00: out = in0;
  endcase
end

endmodule: mux41

gcd/slave.sv
module slave (
  input  logic       clk_i,rst_ni,
  input  logic [3:0] op_a_i, op_b_i,
  input  logic       req_i,

  output logic [3:0] result_val_o,
  output logic       busy_o, valid_o
);
  //declare variable
  logic [3:0] A;
  logic [3:0] B;
  logic [3:0] sub_ab;
  logic [3:0] outa;
  logic [3:0] outb;
  logic [1:0] a_sel;
  logic       b_sel;

  typedef enum logic [1:0] {
    WAIT = 2'd0,
    CALC = 2'd1,
    DONE = 2'd2
  } fsm_state;

  fsm_state state, next_state;

  always_comb begin
      case (state)
        WAIT: begin
          valid_o = 1'b0;
          busy_o  = 1'b0;
          if (req_i) begin
            next_state = CALC;
            a_sel = 2'd0;
            b_sel = 1'b0;
          end
          else  next_state = WAIT;
        end

        CALC: begin
          valid_o = 1'b0;
          busy_o  = 1'b1;
          if (b_zero) begin
            next_state = DONE;
          end
          else if (a_lt) begin
            a_sel = 2'd1;
            b_sel = 1'b1;
            next_state = CALC;
          end
          else begin
            a_sel = 2'd2;
            b_sel = 1'b1;
            next_state = CALC;
          end
        end
        DONE: begin
          valid_o = 1'b1;
          busy_o  = 1'b0;
          next_state = WAIT;
        end
      endcase
  end

  always_ff @(posedge clk_i) begin
    if (!rst_ni)  state <= WAIT;
    else      state <= next_state;
  end

  mux41 muxa(
    .in0(op_a_i),
    .in1(B),
    .in2(sub_ab),
    .in3(4'd0),
    .sel(a_sel),
    .out(outa)
  );

  mux21 muxb(
    .in0(op_b_i),
    .in1(A),
    .sel(b_sel),
    .out(outb)
  );

  dff a_ff(
    .clk_i(clk_i),
    .en(1'b1),
    .d(outa),
    .q(A)
  );

  dff b_ff(
    .clk_i(clk_i),
    .en(1'b1),
    .d(outb),
    .q(B)
  );
  assign b_zero = (B == 0);
  assign a_lt   = ((A < B) ? 1 : 0);
  assign sub_ab = A - B;
  assign result_val_o  = A;

endmodule

src/ifc_gcd.sv
module ifc_gcd(
  input  logic       clk_i,
  input  logic       rst_ni,
  input  logic [3:0] a_data,
  input  logic [3:0] b_data,
  input  logic       a_en,
  input  logic       b_en,
  input  logic       y_en,

  output logic       a_rdy,
  output logic       b_rdy,
  output logic       y_rdy,
  output logic [3:0] y_data
);

  logic [3:0] a_data_mas_to_sla, b_data_mas_to_sla, result_val;
  logic req, busy, valid;

  slave slv(
    .clk_i          (clk_i),
    .rst_ni         (rst_ni),
    .op_a_i         (a_data_mas_to_sla),
    .op_b_i         (b_data_mas_to_sla),
    .req_i          (req),
    .busy_o         (busy),
    .valid_o        (valid),
    .result_val_o   (result_val)
  );

  master mter(
    .op_a_i         (a_data),
    .op_b_i         (b_data),
    .a_en           (a_en),
    .b_en           (b_en),
    .busy_i         (busy),
    .valid_i        (valid),
    .result_val_i   (result_val),
    .result_val_o   (y_data),
    .a_o            (a_data_mas_to_sla),
    .b_o            (b_data_mas_to_sla),
    .clk_i          (clk_i),
    .req_o          (req)
  );

  assign a_rdy = !busy;
  assign b_rdy = !busy;
  assign y_rdy = valid;

// Dump waves
  initial begin
    $dumpfile("dump.vcd");
    $dumpvars(1, ifc_gcd);
  end

endmodule

cocotb/run/dump.vcd
$date
	Sat Aug 26 00:01:36 2023
$end
$version
	Icarus Verilog
$end
$timescale
	1ps
$end
$scope module ifc_gcd $end
$var wire 4 ! a_data [3:0] $end
$var wire 1 " a_en $end
$var wire 4 # b_data [3:0] $end
$var wire 1 $ b_en $end
$var wire 1 % clk_i $end
$var wire 1 & rst_ni $end
$var wire 1 ' y_en $end
$var wire 1 ( y_rdy $end
$var wire 4 ) y_data [3:0] $end
$var wire 1 * valid $end
$var wire 4 + result_val [3:0] $end
$var wire 1 , req $end
$var wire 1 - busy $end
$var wire 1 . b_rdy $end
$var wire 4 / b_data_mas_to_sla [3:0] $end
$var wire 1 0 a_rdy $end
$var wire 4 1 a_data_mas_to_sla [3:0] $end
$upscope $end
$enddefinitions $end
$comment Show the parameter values. $end
$dumpall
$end
#0
$dumpvars
bx 1
x0
bx /
x.
x-
x,
bx +
x*
bx )
x(
z'
1&
0%
z$
bz #
z"
bz !
$end
#1000
b0 )
1.
10
0-
0(
0*
0&
#2000
1&
#5000
b11 !
1"
0,
1%
#10000
0%
#15000
b111 #
1$
0"
b11 1
1%
#20000
0%
#25000
0$
b11 +
b111 /
1%
#30000
0%
#35000
1,
1%
#40000
0%
#45000
0.
00
1-
b0 /
b0 1
1%
#50000
0%
#55000
b111 +
1%
#60000
0%
#65000
b100 +
1%
#70000
0%
#75000
b1 +
1%
#80000
0%
#85000
b11 +
1%
#90000
0%
#95000
b10 +
1%
#100000
0%
#105000
b1 +
1%
#110000
0%
#115000
b0 +
1%
#120000
0%
#125000
b1 +
1%
#130000
0%
#135000
1'
b1 )
1(
1*
1%
#140000
0%
#145000
b0 )
1.
10
0-
0(
0*
1%
